dreifus/__init__.py
dreifus/camera.py
dreifus/camera_bundle.py
dreifus/graphics.py
dreifus/image.py
dreifus/pyvista.py
dreifus/render.py
dreifus/trajectory.py
dreifus/matrix/__init__.py
dreifus/matrix/intrinsics_numpy.py
dreifus/matrix/intrinsics_torch.py
dreifus/matrix/pose_base.py
dreifus/matrix/pose_numpy.py
dreifus/matrix/pose_torch.py
dreifus/matrix/transform_numpy.py
dreifus/util/__init__.py
dreifus/util/colormap.py
dreifus/util/mesh.py
dreifus/util/typing.py
dreifus/util/visualizer.py
dreifus/vector/__init__.py
dreifus/vector/vector_base.py
dreifus/vector/vector_numpy.py
dreifus/vector/vector_torch.py
dreifus-0.1.25.dist-info/METADATA
dreifus-0.1.25.dist-info/WHEEL
dreifus-0.1.25.dist-info/top_level.txt
dreifus-0.1.25.dist-info/RECORD
