Metadata-Version: 2.4
Name: dreifus
Version: 0.1.25
Summary: dreifus lifts your 3D camera experience and facilitates computer vision applications
Author-email: Tobias Kirschstein <tobias.kirschstein@gmail.com>
License: Apache 2.0
Classifier: Development Status :: 3 - Alpha
Classifier: Programming Language :: Python :: 3
Classifier: Operating System :: OS Independent
Requires-Python: >=3.7.0
Requires-Dist: opencv-python>=4.6
Requires-Dist: numpy
Requires-Dist: scipy
Requires-Dist: trimesh
Requires-Dist: pyvista>=0.39
Requires-Dist: dearpygui
Provides-Extra: dev
